goodfaith/__init__.py
goodfaith/__main__.py
goodfaith/core/__init__.py
goodfaith/core/graph.py
goodfaith/core/scope.py
goodfaith-1.0.6.dist-info/LICENSE
goodfaith-1.0.6.dist-info/METADATA
goodfaith-1.0.6.dist-info/WHEEL
goodfaith-1.0.6.dist-info/entry_points.txt
goodfaith-1.0.6.dist-info/top_level.txt
goodfaith-1.0.6.dist-info/RECORD
