Metadata-Version: 2.1
Name: goodfaith
Version: 1.0.6
Summary: hack with 'goodfaith'
Home-page: https://github.com/brevityinmotion/goodfaith
Author: Ryan Elkins
Author-email: ryan@brevityinmotion.com
Project-URL: Bug Tracker, https://github.com/brevityinmotion/goodfaith/issues
Classifier: Programming Language :: Python :: 3
Classifier: License :: OSI Approved :: GNU General Public License v3 (GPLv3)
Requires-Python: >=3.6
License-File: LICENSE
Requires-Dist: pandas
Requires-Dist: tldextract
Requires-Dist: argparse
Requires-Dist: regex
Requires-Dist: networkx
Requires-Dist: bokeh
Requires-Dist: scipy
